pykrieg/__init__.py
pykrieg/board.py
pykrieg/combat.py
pykrieg/constants.py
pykrieg/fen.py
pykrieg/kfen.py
pykrieg/movement.py
pykrieg/pieces.py
pykrieg/py.typed
pykrieg/turn.py
pykrieg/types.py
pykrieg/undo_redo.py
pykrieg/victory.py
pykrieg-0.3.0.dist-info/licenses/LICENSE
pykrieg-0.3.0.dist-info/METADATA
pykrieg-0.3.0.dist-info/WHEEL
pykrieg-0.3.0.dist-info/top_level.txt
pykrieg-0.3.0.dist-info/RECORD
