Metadata-Version: 2.4
Name: pykrieg
Version: 0.3.0
Summary: A Pythonic wargame engine for Guy Debord's Le Jeu de la Guerre
Author-email: ssjmarx <ssjmarx@users.noreply.github.com>
License: GPL-3.0
Project-URL: Homepage, https://github.com/ssjmarx/pykrieg
Project-URL: Documentation, https://pykrieg.readthedocs.io/en/latest/
Project-URL: Repository, https://github.com/ssjmarx/pykrieg
Project-URL: Issues, https://github.com/ssjmarx/pykrieg/issues
Project-URL: PyPI, https://pypi.org/project/pykrieg/
Keywords: wargame,game,engine,debord,strategy,board game
Classifier: Development Status :: 3 - Alpha
Classifier: Intended Audience :: Developers
Classifier: License :: OSI Approved :: GNU General Public License v3 (GPLv3)
Classifier: Programming Language :: Python :: 3
Classifier: Programming Language :: Python :: 3.8
Classifier: Programming Language :: Python :: 3.9
Classifier: Programming Language :: Python :: 3.10
Classifier: Programming Language :: Python :: 3.11
Classifier: Programming Language :: Python :: 3.12
Classifier: Topic :: Games/Entertainment :: Board Games
Classifier: Topic :: Software Development :: Libraries :: Python Modules
Requires-Python: >=3.8
License-File: LICENSE
Provides-Extra: dev
Requires-Dist: pytest>=8.0.0; extra == "dev"
Requires-Dist: pytest-cov>=4.0.0; extra == "dev"
Requires-Dist: hypothesis>=6.0.0; extra == "dev"
Provides-Extra: console
Requires-Dist: windows-curses>=2.0.0; extra == "console"
Dynamic: license-file
